{"nodes": [{"id": "pyscandir_module", "label": "Python Module scandir_rs", "file_type": "document", "source_file": "pyscandir/README.md", "source_location": null, "source_url": null, "captured_at": null, "author": null, "contributor": null}, {"id": "background_thread_pattern", "label": "Background Thread Pattern", "file_type": "rationale", "source_file": "pyscandir/README.md", "source_location": null, "source_url": null, "captured_at": null, "author": null, "contributor": null}, {"id": "context_manager_pattern", "label": "Context Manager Pattern", "file_type": "rationale", "source_file": "pyscandir/README.md", "source_location": null, "source_url": null, "captured_at": null, "author": null, "contributor": null}, {"id": "maturin_build", "label": "Maturin Build System", "file_type": "document", "source_file": "pyscandir/README.md", "source_location": null, "source_url": null, "captured_at": null, "author": null, "contributor": null}, {"id": "pyo3_binding", "label": "PyO3 Rust-Python Binding", "file_type": "rationale", "source_file": "pyscandir/README.md", "source_location": null, "source_url": null, "captured_at": null, "author": null, "contributor": null}], "edges": [{"source": "pyscandir_module", "target": "count_api", "relation": "exposes", "confidence": "EXTRACTED", "confidence_score": 1.0, "source_file": "pyscandir/README.md", "source_location": null, "weight": 1.0}, {"source": "pyscandir_module", "target": "walk_api", "relation": "exposes", "confidence": "EXTRACTED", "confidence_score": 1.0, "source_file": "pyscandir/README.md", "source_location": null, "weight": 1.0}, {"source": "pyscandir_module", "target": "scandir_api", "relation": "exposes", "confidence": "EXTRACTED", "confidence_score": 1.0, "source_file": "pyscandir/README.md", "source_location": null, "weight": 1.0}, {"source": "pyscandir_module", "target": "readme_gil_release", "relation": "rationale_for", "confidence": "EXTRACTED", "confidence_score": 1.0, "source_file": "pyscandir/README.md", "source_location": null, "weight": 1.0}, {"source": "pyscandir_module", "target": "pyo3_binding", "relation": "rationale_for", "confidence": "INFERRED", "confidence_score": 0.9, "source_file": "pyscandir/README.md", "source_location": null, "weight": 1.0}, {"source": "pyscandir_module", "target": "maturin_build", "relation": "references", "confidence": "EXTRACTED", "confidence_score": 1.0, "source_file": "pyscandir/README.md", "source_location": null, "weight": 1.0}, {"source": "background_thread_pattern", "target": "count_api", "relation": "rationale_for", "confidence": "EXTRACTED", "confidence_score": 1.0, "source_file": "pyscandir/README.md", "source_location": null, "weight": 1.0}, {"source": "background_thread_pattern", "target": "walk_api", "relation": "rationale_for", "confidence": "EXTRACTED", "confidence_score": 1.0, "source_file": "pyscandir/README.md", "source_location": null, "weight": 1.0}, {"source": "background_thread_pattern", "target": "scandir_api", "relation": "rationale_for", "confidence": "EXTRACTED", "confidence_score": 1.0, "source_file": "pyscandir/README.md", "source_location": null, "weight": 1.0}, {"source": "context_manager_pattern", "target": "count_api", "relation": "rationale_for", "confidence": "EXTRACTED", "confidence_score": 1.0, "source_file": "pyscandir/README.md", "source_location": null, "weight": 1.0}, {"source": "context_manager_pattern", "target": "walk_api", "relation": "rationale_for", "confidence": "EXTRACTED", "confidence_score": 1.0, "source_file": "pyscandir/README.md", "source_location": null, "weight": 1.0}, {"source": "context_manager_pattern", "target": "scandir_api", "relation": "rationale_for", "confidence": "EXTRACTED", "confidence_score": 1.0, "source_file": "pyscandir/README.md", "source_location": null, "weight": 1.0}], "hyperedges": [{"id": "three_main_apis", "label": "Three Main Directory Iteration APIs", "nodes": ["count_api", "walk_api", "scandir_api"], "relation": "form", "confidence": "EXTRACTED", "confidence_score": 1.0, "source_file": "pyscandir/README.md"}]}